werf_chart_repo_doit_tasks/__init__.py
werf_chart_repo_doit_tasks/tasks.py
werf_chart_repo_doit_tasks-1.0.6.dist-info/LICENSE
werf_chart_repo_doit_tasks-1.0.6.dist-info/METADATA
werf_chart_repo_doit_tasks-1.0.6.dist-info/WHEEL
werf_chart_repo_doit_tasks-1.0.6.dist-info/top_level.txt
werf_chart_repo_doit_tasks-1.0.6.dist-info/RECORD
