Metadata-Version: 2.1
Name: werf-chart-repo-doit-tasks
Version: 1.0.6
Summary: Doit Tasks for managing Werf chart repo
Home-page: https://github.com/ilya-lesikov/werf_chart_repo_doit_tasks
Author: Ilya Lesikov
Author-email: ilya@lesikov.com
License: MIT
Platform: UNKNOWN
Classifier: Development Status :: 5 - Production/Stable
Classifier: License :: OSI Approved :: MIT License
Classifier: Programming Language :: Python
Classifier: Programming Language :: Python :: 3.6
Classifier: Programming Language :: Python :: 3.7
Classifier: Programming Language :: Python :: 3.8
Classifier: Programming Language :: Python :: 3.9
Requires-Dist: doit (<0.34,>=0.33.1)
Requires-Dist: yq (<2.12,>=2.11.0)
